toml_update/__init__.py
toml_update/__main__.py
toml_update/update.py
toml_update-0.2.1.dist-info/METADATA
toml_update-0.2.1.dist-info/WHEEL
toml_update-0.2.1.dist-info/entry_points.txt
toml_update-0.2.1.dist-info/top_level.txt
toml_update-0.2.1.dist-info/RECORD
