Metadata-Version: 2.4
Name: toml_update
Version: 0.2.1
Summary: Non-Official package managing tool with official pip installation tool.
Author-email: MovingJu <baramishe@gmail.com>
Requires-Python: >=3.9
Requires-Dist: build>=1.3.0
Requires-Dist: twine>=6.1.0
